example.py
govdata.py
govdata-0.0.9.dist-info/METADATA
govdata-0.0.9.dist-info/WHEEL
govdata-0.0.9.dist-info/top_level.txt
govdata-0.0.9.dist-info/RECORD
