Metadata-Version: 2.1
Name: govdata
Version: 0.0.9
Author: Giancarlo Rizzo
Requires-Dist: Jinja2 ==3.0.3
Requires-Dist: pandas ==1.5.3
Requires-Dist: pretty-errors ==1.2.25
Requires-Dist: pytest ==7.4.3
Requires-Dist: pytest-cov ==4.1.0
Requires-Dist: requests ==2.31.0
Requires-Dist: requests-mock ==1.11.0
Requires-Dist: pytest-cov
Requires-Dist: fastapi
Requires-Dist: kaleido
Requires-Dist: python-multipart
Requires-Dist: uvicorn
